phrase_pickers/__init__.py
phrase_pickers/np_picker.py
phrase_pickers/vp_picker.py
phrase_pickers/res/morpho_semantic_words.csv.gz
phrase_pickers/res/stopwords.txt.gz
phrase_pickers/res/undesirable_words.json.gz
phrase_pickers-0.2.9.dist-info/LICENSE.txt
phrase_pickers-0.2.9.dist-info/METADATA
phrase_pickers-0.2.9.dist-info/WHEEL
phrase_pickers-0.2.9.dist-info/top_level.txt
phrase_pickers-0.2.9.dist-info/RECORD
