Metadata-Version: 2.1
Name: phrase-pickers
Version: 0.2.9
Summary: NLP helpers to parse noun or verb phrases in a sentence using spacy parse tree.
Home-page: https://github.com/LocusAnalytics/phrase_pickers
Author: CAC
Author-email: cac@locus.co
License: Proprietary
Platform: UNKNOWN
Requires-Python: >=3.6
Requires-Dist: spacy (==2.1.3)
